circuitgraph/__init__.py
circuitgraph/circuit.py
circuitgraph/io.py
circuitgraph/logic.py
circuitgraph/props.py
circuitgraph/sat.py
circuitgraph/tx.py
circuitgraph/utils.py
circuitgraph/netlists/adder.v
circuitgraph/netlists/arbiter.v
circuitgraph/netlists/b17_C.bench
circuitgraph/netlists/b17_Cg.v
circuitgraph/netlists/b18_Cg.v
circuitgraph/netlists/b19_Cg.v
circuitgraph/netlists/b20_C.bench
circuitgraph/netlists/b20_Cg.v
circuitgraph/netlists/b22_C.bench
circuitgraph/netlists/b22_Cg.v
circuitgraph/netlists/banyan_128.v
circuitgraph/netlists/banyan_16.v
circuitgraph/netlists/banyan_256.v
circuitgraph/netlists/banyan_32.v
circuitgraph/netlists/banyan_64.v
circuitgraph/netlists/banyan_8.v
circuitgraph/netlists/bar.v
circuitgraph/netlists/c1355.v
circuitgraph/netlists/c1355g.v
circuitgraph/netlists/c17.v
circuitgraph/netlists/c17_assign.v
circuitgraph/netlists/c17_gates.v
circuitgraph/netlists/c17g.v
circuitgraph/netlists/c1908.v
circuitgraph/netlists/c1908g.v
circuitgraph/netlists/c2670.v
circuitgraph/netlists/c2670g.v
circuitgraph/netlists/c3540.v
circuitgraph/netlists/c3540g.v
circuitgraph/netlists/c432.v
circuitgraph/netlists/c432g.v
circuitgraph/netlists/c499.v
circuitgraph/netlists/c499g.v
circuitgraph/netlists/c5315.v
circuitgraph/netlists/c5315g.v
circuitgraph/netlists/c6288.v
circuitgraph/netlists/c6288g.v
circuitgraph/netlists/c7552.v
circuitgraph/netlists/c7552g.v
circuitgraph/netlists/c880.v
circuitgraph/netlists/c880g.v
circuitgraph/netlists/cavlc.v
circuitgraph/netlists/ctrl.v
circuitgraph/netlists/dec.v
circuitgraph/netlists/div.v
circuitgraph/netlists/i2c.v
circuitgraph/netlists/int2float.v
circuitgraph/netlists/log2.v
circuitgraph/netlists/max.v
circuitgraph/netlists/memctrl.v
circuitgraph/netlists/multiplier.v
circuitgraph/netlists/mux_2.v
circuitgraph/netlists/mux_4.v
circuitgraph/netlists/priority_ckt.v
circuitgraph/netlists/router.v
circuitgraph/netlists/s13207.v
circuitgraph/netlists/s27.v
circuitgraph/netlists/s27_unrolled_4.v
circuitgraph-0.2.1.dist-info/LICENSE
circuitgraph-0.2.1.dist-info/METADATA
circuitgraph-0.2.1.dist-info/WHEEL
circuitgraph-0.2.1.dist-info/top_level.txt
circuitgraph-0.2.1.dist-info/RECORD
