Metadata-Version: 2.1
Name: circuitgraph
Version: 0.2.1
Summary: Tools for working with boolean circuits as graphs.
Home-page: https://github.com/circuitgraph/circuitgraph
Author: Ruben Purdy, Joseph Sweeney
Author-email: rpurdy@andrew.cmu.edu, joesweeney@cmu.edu
Project-URL: Documentation, https://circuitgraph.github.io/circuitgraph/
Project-URL: Source, https://github.com/circuitgraph/circuitgraph
Classifier: Programming Language :: Python :: 3
Classifier: License :: OSI Approved :: MIT License
Classifier: Operating System :: OS Independent
Requires-Python: >=3.6
License-File: LICENSE
Requires-Dist: lark
Requires-Dist: networkx
